napari_assistant/__init__.py
napari_assistant/__main__.py
napari_assistant/_categories.py
napari_assistant/_napari_plugin.py
napari_assistant/_undo_redo.py
napari_assistant/_viewer.py
napari_assistant/_workflow_io_utility.py
napari_assistant/_gui/_Assistant.py
napari_assistant/_gui/__init__.py
napari_assistant/_gui/_button_grid.py
napari_assistant/_gui/_category_widget.py
napari_assistant/_gui/icons/any_image.png
napari_assistant/_gui/icons/binarize.png
napari_assistant/_gui/icons/binary_image.png
napari_assistant/_gui/icons/combine.png
napari_assistant/_gui/icons/combine_labels.png
napari_assistant/_gui/icons/compare_label_images.png
napari_assistant/_gui/icons/filter.png
napari_assistant/_gui/icons/generate_code....png
napari_assistant/_gui/icons/intensity_image.png
napari_assistant/_gui/icons/intensity_image_filtered.png
napari_assistant/_gui/icons/intensity_image_with_background.png
napari_assistant/_gui/icons/intensity_image_with_noise.png
napari_assistant/_gui/icons/label.png
napari_assistant/_gui/icons/label_filters.png
napari_assistant/_gui/icons/label_image.png
napari_assistant/_gui/icons/label_image_processed.png
napari_assistant/_gui/icons/label_neighbor_filters.png
napari_assistant/_gui/icons/map.png
napari_assistant/_gui/icons/measure_labeled_image.png
napari_assistant/_gui/icons/measure_labels.png
napari_assistant/_gui/icons/measurement.png
napari_assistant/_gui/icons/mesh.png
napari_assistant/_gui/icons/mesh_image.png
napari_assistant/_gui/icons/parametric_image.png
napari_assistant/_gui/icons/process_labels.png
napari_assistant/_gui/icons/projection.png
napari_assistant/_gui/icons/redo.png
napari_assistant/_gui/icons/remove_background.png
napari_assistant/_gui/icons/remove_noise.png
napari_assistant/_gui/icons/save_and_load_workflows.png
napari_assistant/_gui/icons/search_biii.png
napari_assistant/_gui/icons/search_image.sc.png
napari_assistant/_gui/icons/search_napari_hub.png
napari_assistant/_gui/icons/transform.png
napari_assistant-0.6.0.dist-info/licenses/LICENSE
napari_assistant-0.6.0.dist-info/METADATA
napari_assistant-0.6.0.dist-info/WHEEL
napari_assistant-0.6.0.dist-info/entry_points.txt
napari_assistant-0.6.0.dist-info/top_level.txt
napari_assistant-0.6.0.dist-info/RECORD
