Metadata-Version: 2.4
Name: napari-assistant
Version: 0.6.0
Summary: A pocket calculator like interface to image processing in napari
Home-page: https://github.com/haesleinhuepf/napari-assistant/
Author: Robert Haase, Ryan Savill
Author-email: robert.haase@uni-leipzig.de
License: BSD-3-Clause
Project-URL: Bug Tracker, https://github.com/haesleinhuepf/napari-assistant/issues
Project-URL: Documentation, https://github.com/haesleinhuepf/napari-assistant/
Project-URL: Source Code, https://github.com/haesleinhuepf/napari-assistant
Project-URL: User Support, https://forum.image.sc/
Classifier: Framework :: napari
Classifier: License :: OSI Approved :: BSD License
Classifier: Topic :: Scientific/Engineering :: Image Processing
Classifier: Topic :: Scientific/Engineering :: Information Analysis
Classifier: Programming Language :: Python
Classifier: Programming Language :: Python :: 3
Classifier: Programming Language :: Python :: 3.9
Classifier: Programming Language :: Python :: 3.10
Classifier: Programming Language :: Python :: 3.11
Classifier: Operating System :: OS Independent
Requires-Python: >=3.9
License-File: LICENSE
Requires-Dist: napari-plugin-engine>=0.1.4
Requires-Dist: toolz
Requires-Dist: napari>=0.4.14
Requires-Dist: magicgui
Requires-Dist: numpy!=1.19.4
Requires-Dist: pyperclip
Requires-Dist: loguru
Requires-Dist: jupytext
Requires-Dist: jupyter
Requires-Dist: pandas
Requires-Dist: napari-time-slicer>=0.4.8
Requires-Dist: napari-workflows>=0.2.10
Dynamic: license-file
